LICENSE.txt
MANIFEST.in
README.rst
setup.py
django_redis_sessions_fork.egg-info/PKG-INFO
django_redis_sessions_fork.egg-info/SOURCES.txt
django_redis_sessions_fork.egg-info/dependency_links.txt
django_redis_sessions_fork.egg-info/not-zip-safe
django_redis_sessions_fork.egg-info/requires.txt
django_redis_sessions_fork.egg-info/top_level.txt
redis_sessions_fork/__init__.py
redis_sessions_fork/backend.py
redis_sessions_fork/conf.py
redis_sessions_fork/connection.py
redis_sessions_fork/models.py
redis_sessions_fork/serializers.py
redis_sessions_fork/session.py
redis_sessions_fork/utils.py
redis_sessions_fork/management/__init__.py
redis_sessions_fork/management/commands/__init__.py
redis_sessions_fork/management/commands/flush_orm_sessions.py
redis_sessions_fork/management/commands/flush_redis_sessions.py
redis_sessions_fork/management/commands/migrate_sessions_to_orm.py
redis_sessions_fork/management/commands/migrate_sessions_to_redis.py