Metadata-Version: 1.1
Name: django-redis-sessions-fork
Version: 0.7.0
Summary: Redis Session Backend For Django
Home-page: https://github.com/hellysmile/django-redis-sessions-fork
Author: see AUTHORS
Author-email: hellysmile@gmail.com
License: BSD
Keywords: django,sessions,redis
Platform: UNKNOWN
Classifier: Programming Language :: Python :: 2
Classifier: Programming Language :: Python :: 3
Classifier: Topic :: Software Development :: Libraries :: Python Modules
Classifier: Framework :: Django
Classifier: Environment :: Web Environment
